<?xml version="1.0" encoding="UTF-8"?>
<response><info><statusCode>0</statusCode><messages/><copyright><imageUrl>http://tile21.mqcdn.com/res/mqlogo.gif</imageUrl><imageAltText>© 2010 MapQuest, Inc.</imageAltText><text>© 2010 MapQuest, Inc.</text></copyright></info><route><sessionId>4c6c8e89-019b-0001-02b7-4979-0024e83e3993</sessionId><options><shapeFormat>raw</shapeFormat><generalize>-1.0</generalize><maxLinkId>0</maxLinkId><narrativeType>text</narrativeType><stateBoundaryDisplay>true</stateBoundaryDisplay><countryBoundaryDisplay>true</countryBoundaryDisplay><sideOfStreetDisplay>true</sideOfStreetDisplay><destinationManeuverDisplay>true</destinationManeuverDisplay><avoidTimedConditions>false</avoidTimedConditions><enhancedNarrative>false</enhancedNarrative><timeType>0</timeType><routeType>FASTEST</routeType><locale>en_US</locale><unit>M</unit><tryAvoidLinkIds></tryAvoidLinkIds><mustAvoidLinkIds></mustAvoidLinkIds><manmaps>true</manmaps></options><boundingBox><ul><lat>36.185138</lat><lng>-86.940116</lng></ul><lr><lat>32.554519</lat><lng>-85.481231</lng></lr></boundingBox><distance>310.2900085449219</distance><time>18209</time><formattedTime>05:03:29</formattedTime><legs><leg><distance>310.29</distance><time>18209</time><formattedTime>05:03:29</formattedTime><index>0</index><maneuvers><maneuver><startPoint><lat>36.185138</lat><lng>-86.768287</lng></startPoint><maneuverNotes/><distance>0.093</distance><time>22</time><formattedTime>00:00:22</formattedTime><attributes>0</attributes><turnType>2</turnType><direction>4</direction><narrative>Start out going SOUTH on MERIDIAN ST toward ARRINGTON ST.</narrative><directionName>South</directionName><index>0</index><streets><street>MERIDIAN ST</street></streets><signs/><iconUrl><![CDATA[http://content.mapquest.com/mqsite/turnsigns/rs_right_sm.gif]]></iconUrl><linkIds/><mapUrl><![CDATA[http://www.mapquestapi.com/staticmap/v3/getmap?type=map&size=225,160&pois=purple-2,36.185138,-86.768287,0,0|purple-3,36.183811,-86.768478,0,0|&center=36.1844745,-86.7683825&zoom=13&key=Dmjtd|luu725uyn5,2x=o5-5zb0d&rand=1965438145&session=4c6c8e89-019b-0001-02b7-4979-0024e83e3993]]></mapUrl></maneuver><maneuver><startPoint><lat>36.183811</lat><lng>-86.768478</lng></startPoint><maneuverNotes/><distance>0.296</distance><time>73</time><formattedTime>00:01:13</formattedTime><attributes>0</attributes><turnType>2</turnType><direction>7</direction><narrative>Turn RIGHT onto HANCOCK ST.</narrative><directionName>West</directionName><index>1</index><streets><street>HANCOCK ST</street></streets><signs/><iconUrl><![CDATA[http://content.mapquest.com/mqsite/turnsigns/rs_right_sm.gif]]></iconUrl><linkIds/><mapUrl><![CDATA[http://www.mapquestapi.com/staticmap/v3/getmap?type=map&size=225,160&pois=purple-3,36.183811,-86.768478,0,0|purple-4,36.184398,-86.773712,0,0|&center=36.184104500000004,-86.771095&zoom=12&key=Dmjtd|luu725uyn5,2x=o5-5zb0d&rand=1965438145&session=4c6c8e89-019b-0001-02b7-4979-0024e83e3993]]></mapUrl></maneuver><maneuver><startPoint><lat>36.184398</lat><lng>-86.773712</lng></startPoint><maneuverNotes/><distance>0.522</distance><time>75</time><formattedTime>00:01:15</formattedTime><attributes>0</attributes><turnType>6</turnType><direction>4</direction><narrative>Turn LEFT onto N 1ST ST/US-31W/US-41/US-431/TN-11. Continue to follow N 1ST ST.</narrative><directionName>South</directionName><index>2</index><streets><street>N 1ST ST</street></streets><signs/><iconUrl><![CDATA[http://content.mapquest.com/mqsite/turnsigns/rs_left_sm.gif]]></iconUrl><linkIds/><mapUrl><![CDATA[http://www.mapquestapi.com/staticmap/v3/getmap?type=map&size=225,160&pois=purple-4,36.184398,-86.773712,0,0|purple-5,36.17691,-86.774551,0,0|&center=36.180654000000004,-86.77413150000001&zoom=10&key=Dmjtd|luu725uyn5,2x=o5-5zb0d&rand=1965438145&session=4c6c8e89-019b-0001-02b7-4979-0024e83e3993]]></mapUrl></maneuver><maneuver><startPoint><lat>36.17691</lat><lng>-86.774551</lng></startPoint><maneuverNotes/><distance>0.03</distance><time>6</time><formattedTime>00:00:06</formattedTime><attributes>0</attributes><turnType>6</turnType><direction>8</direction><narrative>Turn LEFT onto SPRING ST.</narrative><directionName>East</directionName><index>3</index><streets><street>SPRING ST</street></streets><signs/><iconUrl><![CDATA[http://content.mapquest.com/mqsite/turnsigns/rs_left_sm.gif]]></iconUrl><linkIds/><mapUrl><![CDATA[http://www.mapquestapi.com/staticmap/v3/getmap?type=map&size=225,160&pois=purple-5,36.17691,-86.774551,0,0|purple-6,36.176799,-86.774032,0,0|&center=36.176854500000005,-86.7742915&zoom=15&key=Dmjtd|luu725uyn5,2x=o5-5zb0d&rand=1965438145&session=4c6c8e89-019b-0001-02b7-4979-0024e83e3993]]></mapUrl></maneuver><maneuver><startPoint><lat>36.176799</lat><lng>-86.774032</lng></startPoint><maneuverNotes/><distance>1.584</distance><time>134</time><formattedTime>00:02:14</formattedTime><attributes>128</attributes><turnType>10</turnType><direction>8</direction><narrative>Merge onto I-24 E.</narrative><directionName>East</directionName><index>4</index><streets><street>INTERSTATE 24 E</street></streets><signs><sign><type>1</type><direction>8</direction><text>24</text><extraText></extraText><url><![CDATA[http://api-signs.mqcdn.com/?s=rs&t=RS00001CO_SM&n=24&d=EAST]]></url></sign></signs><iconUrl><![CDATA[http://content.mapquest.com/mqsite/turnsigns/rs_merge_right_sm.gif]]></iconUrl><linkIds/><mapUrl><![CDATA[http://www.mapquestapi.com/staticmap/v3/getmap?type=map&size=225,160&pois=purple-6,36.176799,-86.774032,0,0|purple-7,36.157688,-86.760406,0,0|&center=36.1672435,-86.76721900000001&zoom=9&key=Dmjtd|luu725uyn5,2x=o5-5zb0d&rand=1965438145&session=4c6c8e89-019b-0001-02b7-4979-0024e83e3993]]></mapUrl></maneuver><maneuver><startPoint><lat>36.157688</lat><lng>-86.760406</lng></startPoint><maneuverNotes/><distance>1.047</distance><time>92</time><formattedTime>00:01:32</formattedTime><attributes>128</attributes><turnType>10</turnType><direction>7</direction><narrative>Merge onto I-40 W via EXIT 50B toward I-65 S/MEMPHIS/HUNTSVILLE.</narrative><directionName>West</directionName><index>5</index><streets><street>INTERSTATE 40 W</street></streets><signs><sign><type>1</type><direction>7</direction><text>40</text><extraText></extraText><url><![CDATA[http://api-signs.mqcdn.com/?s=rs&t=RS00001CO_SM&n=40&d=WEST]]></url></sign><sign><type>1001</type><direction>0</direction><text>50B</text><extraText></extraText><url><![CDATA[http://api-signs.mqcdn.com/?s=rs&t=RSEXITRIGHTNUM_SM&n=50B&d=]]></url></sign></signs><iconUrl><![CDATA[http://content.mapquest.com/mqsite/turnsigns/rs_merge_right_sm.gif]]></iconUrl><linkIds/><mapUrl><![CDATA[http://www.mapquestapi.com/staticmap/v3/getmap?type=map&size=225,160&pois=purple-7,36.157688,-86.760406,0,0|purple-8,36.149211,-86.774963,0,0|&center=36.1534495,-86.7676845&zoom=10&key=Dmjtd|luu725uyn5,2x=o5-5zb0d&rand=1965438145&session=4c6c8e89-019b-0001-02b7-4979-0024e83e3993]]></mapUrl></maneuver><maneuver><startPoint><lat>36.149211</lat><lng>-86.774963</lng></startPoint><maneuverNotes/><distance>188.83301</distance><time>10207</time><formattedTime>02:50:07</formattedTime><attributes>128</attributes><turnType>11</turnType><direction>4</direction><narrative>Merge onto I-65 S via EXIT 210B on the LEFT toward HUNTSVILLE (Crossing into ALABAMA).</narrative><directionName>South</directionName><index>6</index><streets><street>INTERSTATE 65 S</street></streets><signs><sign><type>1</type><direction>4</direction><text>65</text><extraText></extraText><url><![CDATA[http://api-signs.mqcdn.com/?s=rs&t=RS00001CO_SM&n=65&d=SOUTH]]></url></sign><sign><type>1001</type><direction>0</direction><text>210B</text><extraText></extraText><url><![CDATA[http://api-signs.mqcdn.com/?s=rs&t=RSEXITLEFTNUM_SM&n=210B&d=]]></url></sign></signs><iconUrl><![CDATA[http://content.mapquest.com/mqsite/turnsigns/rs_merge_left_sm.gif]]></iconUrl><linkIds/><mapUrl><![CDATA[http://www.mapquestapi.com/staticmap/v3/getmap?type=map&size=225,160&pois=purple-8,36.149211,-86.774963,0,0|purple-9,33.523189,-86.826721,0,0|&center=34.836200000000005,-86.852096&zoom=2&key=Dmjtd|luu725uyn5,2x=o5-5zb0d&rand=1965438145&session=4c6c8e89-019b-0001-02b7-4979-0024e83e3993]]></mapUrl></maneuver><maneuver><startPoint><lat>33.523189</lat><lng>-86.826721</lng></startPoint><maneuverNotes/><distance>1.234</distance><time>94</time><formattedTime>00:01:34</formattedTime><attributes>128</attributes><turnType>11</turnType><direction>8</direction><narrative>Merge onto I-20 E/I-59 N via EXIT 261A on the LEFT toward ATLANTA/GADSDEN.</narrative><directionName>East</directionName><index>7</index><streets><street>INTERSTATE 20 E</street><street>INTERSTATE 59 N</street></streets><signs><sign><type>1</type><direction>8</direction><text>20</text><extraText></extraText><url><![CDATA[http://api-signs.mqcdn.com/?s=rs&t=RS00001CO_SM&n=20&d=EAST]]></url></sign><sign><type>1</type><direction>1</direction><text>59</text><extraText></extraText><url><![CDATA[http://api-signs.mqcdn.com/?s=rs&t=RS00001CO_SM&n=59&d=NORTH]]></url></sign><sign><type>1001</type><direction>0</direction><text>261A</text><extraText></extraText><url><![CDATA[http://api-signs.mqcdn.com/?s=rs&t=RSEXITLEFTNUM_SM&n=261A&d=]]></url></sign></signs><iconUrl><![CDATA[http://content.mapquest.com/mqsite/turnsigns/rs_merge_left_sm.gif]]></iconUrl><linkIds/><mapUrl><![CDATA[http://www.mapquestapi.com/staticmap/v3/getmap?type=map&size=225,160&pois=purple-9,33.523189,-86.826721,0,0|purple-10,33.52423,-86.807746,0,0|&center=33.522014,-86.8172335&zoom=10&key=Dmjtd|luu725uyn5,2x=o5-5zb0d&rand=1965438145&session=4c6c8e89-019b-0001-02b7-4979-0024e83e3993]]></mapUrl></maneuver><maneuver><startPoint><lat>33.52423</lat><lng>-86.807746</lng></startPoint><maneuverNotes/><distance>3.204</distance><time>247</time><formattedTime>00:04:07</formattedTime><attributes>128</attributes><turnType>10</turnType><direction>8</direction><narrative>Merge onto US-280 E/US-31 S/ELTON B STEPHENS EXPY/AL-3 S via EXIT 126A.</narrative><directionName>East</directionName><index>8</index><streets><street>US HIGHWAY 280 E</street><street>US HIGHWAY 31 S</street><street>ELTON B STEPHENS EXPY</street><street>STATE ROUTE 3 S</street></streets><signs><sign><type>2</type><direction>8</direction><text>280</text><extraText></extraText><url><![CDATA[http://api-signs.mqcdn.com/?s=rs&t=RS00002BW_SM&n=280&d=EAST]]></url></sign><sign><type>2</type><direction>4</direction><text>31</text><extraText></extraText><url><![CDATA[http://api-signs.mqcdn.com/?s=rs&t=RS00002BW_SM&n=31&d=SOUTH]]></url></sign><sign><type>3</type><direction>4</direction><text>3</text><extraText></extraText><url><![CDATA[http://api-signs.mqcdn.com/?s=rs&t=RS00003BW_SM&n=3&d=SOUTH]]></url></sign><sign><type>1001</type><direction>0</direction><text>126A</text><extraText></extraText><url><![CDATA[http://api-signs.mqcdn.com/?s=rs&t=RSEXITRIGHTNUM_SM&n=126A&d=]]></url></sign></signs><iconUrl><![CDATA[http://content.mapquest.com/mqsite/turnsigns/rs_merge_right_sm.gif]]></iconUrl><linkIds/><mapUrl><![CDATA[http://www.mapquestapi.com/staticmap/v3/getmap?type=map&size=225,160&pois=purple-10,33.52423,-86.807746,0,0|purple-11,33.48822,-86.786872,0,0|&center=33.506994,-86.797309&zoom=8&key=Dmjtd|luu725uyn5,2x=o5-5zb0d&rand=1975826365&session=4c6c8e89-019b-0001-02b7-4979-0024e83e3993]]></mapUrl></maneuver><maneuver><startPoint><lat>33.48822</lat><lng>-86.786872</lng></startPoint><maneuverNotes/><distance>101.94401</distance><time>6238</time><formattedTime>01:43:58</formattedTime><attributes>0</attributes><turnType>10</turnType><direction>8</direction><narrative>Merge onto US-280 E/AL-38 E toward SYLACAUGA/ZOO-GARDENS.</narrative><directionName>East</directionName><index>9</index><streets><street>US HIGHWAY 280 E</street><street>STATE ROUTE 38 E</street></streets><signs><sign><type>2</type><direction>8</direction><text>280</text><extraText></extraText><url><![CDATA[http://api-signs.mqcdn.com/?s=rs&t=RS00002BW_SM&n=280&d=EAST]]></url></sign><sign><type>3</type><direction>8</direction><text>38</text><extraText></extraText><url><![CDATA[http://api-signs.mqcdn.com/?s=rs&t=RS00003BW_SM&n=38&d=EAST]]></url></sign></signs><iconUrl><![CDATA[http://content.mapquest.com/mqsite/turnsigns/rs_merge_right_sm.gif]]></iconUrl><linkIds/><mapUrl><![CDATA[http://www.mapquestapi.com/staticmap/v3/getmap?type=map&size=225,160&pois=purple-11,33.48822,-86.786872,0,0|purple-12,32.6763,-85.486328,0,0|&center=33.08226,-86.1366&zoom=4&key=Dmjtd|luu725uyn5,2x=o5-5zb0d&rand=1975826365&session=4c6c8e89-019b-0001-02b7-4979-0024e83e3993]]></mapUrl></maneuver><maneuver><startPoint><lat>32.6763</lat><lng>-85.486328</lng></startPoint><maneuverNotes/><distance>2.857</distance><time>214</time><formattedTime>00:03:34</formattedTime><attributes>0</attributes><turnType>2</turnType><direction>4</direction><narrative>Turn RIGHT onto AL-147.</narrative><directionName>South</directionName><index>10</index><streets><street>STATE ROUTE 147</street></streets><signs><sign><type>3</type><direction>0</direction><text>147</text><extraText></extraText><url><![CDATA[http://api-signs.mqcdn.com/?s=rs&t=RS00003BW_SM&n=147]]></url></sign></signs><iconUrl><![CDATA[http://content.mapquest.com/mqsite/turnsigns/rs_right_sm.gif]]></iconUrl><linkIds/><mapUrl><![CDATA[http://www.mapquestapi.com/staticmap/v3/getmap?type=map&size=225,160&pois=purple-12,32.6763,-85.486328,0,0|purple-13,32.637149,-85.481666,0,0|&center=32.656724499999996,-85.48603750000001&zoom=8&key=Dmjtd|luu725uyn5,2x=o5-5zb0d&rand=1975826365&session=4c6c8e89-019b-0001-02b7-4979-0024e83e3993]]></mapUrl></maneuver><maneuver><startPoint><lat>32.637149</lat><lng>-85.481666</lng></startPoint><maneuverNotes/><distance>5.052</distance><time>386</time><formattedTime>00:06:26</formattedTime><attributes>0</attributes><turnType>1</turnType><direction>6</direction><narrative>Turn SLIGHT RIGHT onto AL-267/SHUG JORDAN PKWY.</narrative><directionName>Southwest</directionName><index>11</index><streets><street>STATE ROUTE 267</street><street>SHUG JORDAN PKWY</street></streets><signs><sign><type>3</type><direction>0</direction><text>267</text><extraText></extraText><url><![CDATA[http://api-signs.mqcdn.com/?s=rs&t=RS00003BW_SM&n=267]]></url></sign></signs><iconUrl><![CDATA[http://content.mapquest.com/mqsite/turnsigns/rs_slight_right_sm.gif]]></iconUrl><linkIds/><mapUrl><![CDATA[http://www.mapquestapi.com/staticmap/v3/getmap?type=map&size=225,160&pois=purple-13,32.637149,-85.481666,0,0|purple-14,32.57796,-85.498443,0,0|&center=32.6075545,-85.49468949999999&zoom=7&key=Dmjtd|luu725uyn5,2x=o5-5zb0d&rand=1975826365&session=4c6c8e89-019b-0001-02b7-4979-0024e83e3993]]></mapUrl></maneuver><maneuver><startPoint><lat>32.57796</lat><lng>-85.498443</lng></startPoint><maneuverNotes/><distance>1.706</distance><time>155</time><formattedTime>00:02:35</formattedTime><attributes>0</attributes><turnType>1</turnType><direction>6</direction><narrative>Turn SLIGHT RIGHT onto S COLLEGE ST/AL-147. Continue to follow S COLLEGE ST.</narrative><directionName>Southwest</directionName><index>12</index><streets><street>S COLLEGE ST</street></streets><signs/><iconUrl><![CDATA[http://content.mapquest.com/mqsite/turnsigns/rs_slight_right_sm.gif]]></iconUrl><linkIds/><mapUrl><![CDATA[http://www.mapquestapi.com/staticmap/v3/getmap?type=map&size=225,160&pois=purple-14,32.57796,-85.498443,0,0|purple-15,32.55513,-85.508186,0,0|&center=32.566545,-85.503116&zoom=8&key=Dmjtd|luu725uyn5,2x=o5-5zb0d&rand=1975826365&session=4c6c8e89-019b-0001-02b7-4979-0024e83e3993]]></mapUrl></maneuver><maneuver><startPoint><lat>32.55513</lat><lng>-85.508186</lng></startPoint><maneuverNotes/><distance>1.021</distance><time>129</time><formattedTime>00:02:09</formattedTime><attributes>0</attributes><turnType>6</turnType><direction>8</direction><narrative>Turn LEFT onto CR-863/SHELL TOOMER PKWY.</narrative><directionName>East</directionName><index>13</index><streets><street>COUNTY ROUTE 863</street><street>SHELL TOOMER PKWY</street></streets><signs><sign><type>4</type><direction>0</direction><text>863</text><extraText></extraText></sign></signs><iconUrl><![CDATA[http://content.mapquest.com/mqsite/turnsigns/rs_left_sm.gif]]></iconUrl><linkIds/><mapUrl><![CDATA[http://www.mapquestapi.com/staticmap/v3/getmap?type=map&size=225,160&pois=purple-15,32.55513,-85.508186,0,0|purple-16,32.55466,-85.490821,0,0|&center=32.554824499999995,-85.4995035&zoom=10&key=Dmjtd|luu725uyn5,2x=o5-5zb0d&rand=1975826365&session=4c6c8e89-019b-0001-02b7-4979-0024e83e3993]]></mapUrl></maneuver><maneuver><startPoint><lat>32.55466</lat><lng>-85.490821</lng></startPoint><maneuverNotes/><distance>0.818</distance><time>130</time><formattedTime>00:02:10</formattedTime><attributes>0</attributes><turnType>6</turnType><direction>1</direction><narrative>Turn LEFT onto CANARY DR.</narrative><directionName>North</directionName><index>14</index><streets><street>CANARY DR</street></streets><signs/><iconUrl><![CDATA[http://content.mapquest.com/mqsite/turnsigns/rs_left_sm.gif]]></iconUrl><linkIds/><mapUrl><![CDATA[http://www.mapquestapi.com/staticmap/v3/getmap?type=map&size=225,160&pois=purple-16,32.55466,-85.490821,0,0|purple-17,32.566139,-85.489463,0,0|&center=32.5603995,-85.49039400000001&zoom=9&key=Dmjtd|luu725uyn5,2x=o5-5zb0d&rand=1975826365&session=4c6c8e89-019b-0001-02b7-4979-0024e83e3993]]></mapUrl></maneuver><maneuver><startPoint><lat>32.566139</lat><lng>-85.489463</lng></startPoint><maneuverNotes/><distance>0.049</distance><time>7</time><formattedTime>00:00:07</formattedTime><attributes>0</attributes><turnType>2</turnType><direction>3</direction><narrative>Turn RIGHT to stay on CANARY DR.</narrative><directionName>Northeast</directionName><index>15</index><streets><street>CANARY DR</street></streets><signs/><iconUrl><![CDATA[http://content.mapquest.com/mqsite/turnsigns/rs_right_sm.gif]]></iconUrl><linkIds/><mapUrl><![CDATA[http://www.mapquestapi.com/staticmap/v3/getmap?type=map&size=225,160&pois=purple-17,32.566139,-85.489463,0,0|purple-18,32.566478,-85.488723,0,0|&center=32.5663085,-85.489093&zoom=15&key=Dmjtd|luu725uyn5,2x=o5-5zb0d&rand=1975826365&session=4c6c8e89-019b-0001-02b7-4979-0024e83e3993]]></mapUrl></maneuver><maneuver><startPoint/><maneuverNotes/><distance>0.0</distance><time>0</time><formattedTime>00:00:00</formattedTime><attributes>0</attributes><turnType>-1</turnType><direction>0</direction><narrative>1963 CANARY DR is on the RIGHT.</narrative><directionName></directionName><index>16</index><streets/><signs/><linkIds/><mapUrl><![CDATA[]]></mapUrl></maneuver></maneuvers><hasTollRoad>false</hasTollRoad><hasFerry>false</hasFerry><hasHighway>true</hasHighway><hasSeasonalClosure>false</hasSeasonalClosure><hasUnpaved>false</hasUnpaved><hasCountryCross>false</hasCountryCross></leg></legs><hasTollRoad>false</hasTollRoad><hasFerry>false</hasFerry><hasHighway>true</hasHighway><hasSeasonalClosure>false</hasSeasonalClosure><hasUnpaved>false</hasUnpaved><hasCountryCross>false</hasCountryCross><locations><location><street>816 Meridian St</street><adminArea5 type="City">Nashville</adminArea5><adminArea3 type="State">TN</adminArea3><adminArea4 type="County">Davidson County</adminArea4><postalCode>37207-5850</postalCode><adminArea1 type="Country">US</adminArea1><geocodeQuality>POINT</geocodeQuality><geocodeQualityCode>P1AAA</geocodeQualityCode><dragPoint>false</dragPoint><sideOfStreet>L</sideOfStreet><displayLatLng><latLng><lat>36.185138</lat><lng>-86.76828</lng></latLng></displayLatLng><linkId>31393483</linkId><type>s</type><latLng><lat>36.18514</lat><lng>-86.76828</lng></latLng></location><location><street>1963 Canary Dr</street><adminArea5 type="City">Auburn</adminArea5><adminArea3 type="State">AL</adminArea3><adminArea4 type="County">Lee County</adminArea4><postalCode>36830-6901</postalCode><adminArea1 type="Country">US</adminArea1><geocodeQuality>POINT</geocodeQuality><geocodeQualityCode>P1AAA</geocodeQualityCode><dragPoint>false</dragPoint><sideOfStreet>R</sideOfStreet><displayLatLng><latLng><lat>32.566478</lat><lng>-85.488723</lng></latLng></displayLatLng><linkId>105113616</linkId><type>s</type><latLng><lat>32.56648</lat><lng>-85.48872</lng></latLng></location></locations><locationSequence>0,1</locationSequence></route></response>